<?xml version="1.0" encoding="UTF-8"?>
<java version="14.0.2" class="java.beans.XMLDecoder">
 <object class="org.eclipse.epp.internal.mpc.ui.catalog.MarketplaceInfo" id="MarketplaceInfo0">
  <void property="iuToNodeKey">
   <void method="put">
    <string>org.eclipse.embedcdt.templates.stm</string>
    <object class="java.util.ArrayList">
     <void method="add">
      <string>https://marketplace.eclipse.org#2593184</string>
     </void>
    </object>
   </void>
   <void method="put">
    <string>com.ibm.ws.appconversion_feature.weblogic</string>
    <object class="java.util.ArrayList">
     <void method="add">
      <string>https://marketplace.eclipse.org#1744576</string>
     </void>
    </object>
   </void>
   <void method="put">
    <string>Stack_Pasta</string>
    <object class="java.util.ArrayList">
     <void method="add">
      <string>https://marketplace.eclipse.org#5239166</string>
     </void>
    </object>
   </void>
   <void method="put">
    <string>org.faktorips.feature</string>
    <object class="java.util.ArrayList">
     <void method="add">
      <string>https://marketplace.eclipse.org#391</string>
     </void>
    </object>
   </void>
   <void method="put">
    <string>com.ibm.ws.appconversion_feature.was2was</string>
    <object class="java.util.ArrayList">
     <void method="add">
      <string>https://marketplace.eclipse.org#1744576</string>
     </void>
    </object>
   </void>
   <void method="put">
    <string>org.eclipse.wildwebdeveloper.embedder.node.feature</string>
    <object class="java.util.ArrayList">
     <void method="add">
      <string>https://marketplace.eclipse.org#2963400</string>
     </void>
    </object>
   </void>
   <void method="put">
    <string>org.eclipse.wst.xml_ui.feature</string>
    <object class="java.util.ArrayList">
     <void method="add">
      <string>https://marketplace.eclipse.org#2963400</string>
     </void>
    </object>
   </void>
   <void method="put">
    <string>org.eclipse.embedcdt.codered</string>
    <object class="java.util.ArrayList">
     <void method="add">
      <string>https://marketplace.eclipse.org#2593184</string>
     </void>
    </object>
   </void>
   <void method="put">
    <string>org.eclipse.embedcdt.debug.gdbjtag.pyocd</string>
    <object class="java.util.ArrayList">
     <void method="add">
      <string>https://marketplace.eclipse.org#2593184</string>
     </void>
    </object>
   </void>
   <void method="put">
    <string>org.eclipse.embedcdt.debug.gdbjtag.jlink</string>
    <object class="java.util.ArrayList">
     <void method="add">
      <string>https://marketplace.eclipse.org#2593184</string>
     </void>
    </object>
   </void>
   <void method="put">
    <string>org.eclipse.wst.web_ui.feature</string>
    <object class="java.util.ArrayList">
     <void method="add">
      <string>https://marketplace.eclipse.org#2963400</string>
     </void>
    </object>
   </void>
   <void method="put">
    <string>org.eclipse.egit</string>
    <object class="java.util.ArrayList">
     <void method="add">
      <string>https://marketplace.eclipse.org#2963400</string>
     </void>
    </object>
   </void>
   <void method="put">
    <string>com.hybris.hyeclipse.feature</string>
    <object class="java.util.ArrayList">
     <void method="add">
      <string>https://marketplace.eclipse.org#3565771</string>
     </void>
    </object>
   </void>
   <void method="put">
    <string>org.eclipse.wst.web_js_support.feature</string>
    <object class="java.util.ArrayList">
     <void method="add">
      <string>https://marketplace.eclipse.org#2963400</string>
     </void>
    </object>
   </void>
   <void method="put">
    <string>org.eclipse.embedcdt.templates.cortexm</string>
    <object class="java.util.ArrayList">
     <void method="add">
      <string>https://marketplace.eclipse.org#2593184</string>
     </void>
    </object>
   </void>
   <void method="put">
    <string>com.ibm.ws.migrationtoolkit.cloud.feature</string>
    <object class="java.util.ArrayList">
     <void method="add">
      <string>https://marketplace.eclipse.org#1744576</string>
     </void>
    </object>
   </void>
   <void method="put">
    <string>org.eclipse.embedcdt.packs</string>
    <object class="java.util.ArrayList">
     <void method="add">
      <string>https://marketplace.eclipse.org#2593184</string>
     </void>
    </object>
   </void>
   <void method="put">
    <string>com.ibm.ws.configmigration.tomcat_feature</string>
    <object class="java.util.ArrayList">
     <void method="add">
      <string>https://marketplace.eclipse.org#1744576</string>
     </void>
    </object>
   </void>
   <void method="put">
    <string>com.ibm.ws.appconversion_feature.oracle</string>
    <object class="java.util.ArrayList">
     <void method="add">
      <string>https://marketplace.eclipse.org#1744576</string>
     </void>
    </object>
   </void>
   <void method="put">
    <string>org.moreunit</string>
    <object class="java.util.ArrayList">
     <void method="add">
      <string>https://marketplace.eclipse.org#194</string>
     </void>
    </object>
   </void>
   <void method="put">
    <string>com.codeaffine.gonsole.feature</string>
    <object class="java.util.ArrayList">
     <void method="add">
      <string>https://marketplace.eclipse.org#1789454</string>
     </void>
    </object>
   </void>
   <void method="put">
    <string>org.faktorips.feature.nl1</string>
    <object class="java.util.ArrayList">
     <void method="add">
      <string>https://marketplace.eclipse.org#391</string>
     </void>
    </object>
   </void>
   <void method="put">
    <string>org.eclipse.embedcdt.managedbuild.cross.riscv</string>
    <object class="java.util.ArrayList">
     <void method="add">
      <string>https://marketplace.eclipse.org#2593184</string>
     </void>
    </object>
   </void>
   <void method="put">
    <string>org.eclipse.tips.feature</string>
    <object class="java.util.ArrayList">
     <void method="add">
      <string>https://marketplace.eclipse.org#2963400</string>
     </void>
    </object>
   </void>
   <void method="put">
    <string>org.eclipse.wst.xsl.feature</string>
    <object class="java.util.ArrayList">
     <void method="add">
      <string>https://marketplace.eclipse.org#2963400</string>
     </void>
    </object>
   </void>
   <void method="put">
    <string>com.ibm.ws.appconversion_feature.jboss</string>
    <object class="java.util.ArrayList">
     <void method="add">
      <string>https://marketplace.eclipse.org#1744576</string>
     </void>
    </object>
   </void>
   <void method="put">
    <string>com.codeaffine.gonsole.egit.feature</string>
    <object class="java.util.ArrayList">
     <void method="add">
      <string>https://marketplace.eclipse.org#1789454</string>
     </void>
    </object>
   </void>
   <void method="put">
    <string>org.eclipse.tm.terminal.feature</string>
    <object class="java.util.ArrayList">
     <void method="add">
      <string>https://marketplace.eclipse.org#2963400</string>
     </void>
    </object>
   </void>
   <void method="put">
    <string>org.eclipse.embedcdt.templates.sifive</string>
    <object class="java.util.ArrayList">
     <void method="add">
      <string>https://marketplace.eclipse.org#2593184</string>
     </void>
    </object>
   </void>
   <void method="put">
    <string>net.certiv.codechase.feature</string>
    <object class="java.util.ArrayList">
     <void method="add">
      <string>https://marketplace.eclipse.org#892</string>
     </void>
    </object>
   </void>
   <void method="put">
    <string>org.moreunit.light</string>
    <object class="java.util.ArrayList">
     <void method="add">
      <string>https://marketplace.eclipse.org#194</string>
     </void>
    </object>
   </void>
   <void method="put">
    <string>org.wangzw.cppstyle.feature</string>
    <object class="java.util.ArrayList">
     <void method="add">
      <string>https://marketplace.eclipse.org#2192883</string>
     </void>
    </object>
   </void>
   <void method="put">
    <string>com.github.imkrmgn.javadocdecorator.feature</string>
    <object class="java.util.ArrayList">
     <void method="add">
      <string>https://marketplace.eclipse.org#4799014</string>
     </void>
    </object>
   </void>
   <void method="put">
    <string>org.eclipse.wildwebdeveloper.feature</string>
    <object class="java.util.ArrayList">
     <void method="add">
      <string>https://marketplace.eclipse.org#2963400</string>
     </void>
    </object>
   </void>
   <void method="put">
    <string>zipeditor</string>
    <object class="java.util.ArrayList">
     <void method="add">
      <string>https://marketplace.eclipse.org#1760305</string>
     </void>
    </object>
   </void>
   <void method="put">
    <string>org.eclipse.embedcdt.debug.gdbjtag.qemu</string>
    <object class="java.util.ArrayList">
     <void method="add">
      <string>https://marketplace.eclipse.org#2593184</string>
     </void>
    </object>
   </void>
   <void method="put">
    <string>org.testng.eclipse</string>
    <object class="java.util.ArrayList">
     <void method="add">
      <string>https://marketplace.eclipse.org#1549</string>
     </void>
    </object>
   </void>
   <void method="put">
    <string>org.moreunit.mock</string>
    <object class="java.util.ArrayList">
     <void method="add">
      <string>https://marketplace.eclipse.org#194</string>
     </void>
    </object>
   </void>
   <void method="put">
    <string>org.eclipse.embedcdt.debug.gdbjtag.openocd</string>
    <object class="java.util.ArrayList">
     <void method="add">
      <string>https://marketplace.eclipse.org#2593184</string>
     </void>
    </object>
   </void>
   <void method="put">
    <string>org.eclipse.embedcdt.templates.ad</string>
    <object class="java.util.ArrayList">
     <void method="add">
      <string>https://marketplace.eclipse.org#2593184</string>
     </void>
    </object>
   </void>
   <void method="put">
    <string>com.ibm.ws.appconversion_feature.tomcat</string>
    <object class="java.util.ArrayList">
     <void method="add">
      <string>https://marketplace.eclipse.org#1744576</string>
     </void>
    </object>
   </void>
   <void method="put">
    <string>org.eclipse.wst.server_adapters.feature</string>
    <object class="java.util.ArrayList">
     <void method="add">
      <string>https://marketplace.eclipse.org#2963400</string>
     </void>
    </object>
   </void>
   <void method="put">
    <string>org.eclipse.embedcdt.managedbuild.cross.arm</string>
    <object class="java.util.ArrayList">
     <void method="add">
      <string>https://marketplace.eclipse.org#2593184</string>
     </void>
    </object>
   </void>
   <void method="put">
    <string>org.adichatz.feature</string>
    <object class="java.util.ArrayList">
     <void method="add">
      <string>https://marketplace.eclipse.org#941</string>
     </void>
    </object>
   </void>
   <void method="put">
    <string>org.testng.eclipse.maven.feature</string>
    <object class="java.util.ArrayList">
     <void method="add">
      <string>https://marketplace.eclipse.org#1549</string>
     </void>
    </object>
   </void>
  </void>
  <void property="nodeKeyToIU">
   <void method="put">
    <string>https://marketplace.eclipse.org#194</string>
    <object class="java.util.ArrayList">
     <void method="add">
      <string>org.moreunit</string>
     </void>
     <void method="add">
      <string>org.moreunit.mock</string>
     </void>
     <void method="add">
      <string>org.moreunit.light</string>
     </void>
    </object>
   </void>
   <void method="put">
    <string>https://marketplace.eclipse.org#1760305</string>
    <object class="java.util.ArrayList">
     <void method="add">
      <string>zipeditor</string>
     </void>
    </object>
   </void>
   <void method="put">
    <string>https://marketplace.eclipse.org#391</string>
    <object class="java.util.ArrayList">
     <void method="add">
      <string>org.faktorips.feature</string>
     </void>
     <void method="add">
      <string>org.faktorips.feature.nl1</string>
     </void>
    </object>
   </void>
   <void method="put">
    <string>https://marketplace.eclipse.org#941</string>
    <object class="java.util.ArrayList">
     <void method="add">
      <string>org.adichatz.feature</string>
     </void>
    </object>
   </void>
   <void method="put">
    <string>https://marketplace.eclipse.org#892</string>
    <object class="java.util.ArrayList">
     <void method="add">
      <string>net.certiv.codechase.feature</string>
     </void>
    </object>
   </void>
   <void method="put">
    <string>https://marketplace.eclipse.org#2963400</string>
    <object class="java.util.ArrayList">
     <void method="add">
      <string>org.eclipse.wst.web_ui.feature</string>
     </void>
     <void method="add">
      <string>org.eclipse.wst.xsl.feature</string>
     </void>
     <void method="add">
      <string>org.eclipse.wildwebdeveloper.feature</string>
     </void>
     <void method="add">
      <string>org.eclipse.wst.server_adapters.feature</string>
     </void>
     <void method="add">
      <string>org.eclipse.tm.terminal.feature</string>
     </void>
     <void method="add">
      <string>org.eclipse.egit</string>
     </void>
     <void method="add">
      <string>org.eclipse.tips.feature</string>
     </void>
     <void method="add">
      <string>org.eclipse.wst.xml_ui.feature</string>
     </void>
     <void method="add">
      <string>org.eclipse.wildwebdeveloper.embedder.node.feature</string>
     </void>
     <void method="add">
      <string>org.eclipse.wst.web_js_support.feature</string>
     </void>
    </object>
   </void>
   <void method="put">
    <string>https://marketplace.eclipse.org#1549</string>
    <object class="java.util.ArrayList">
     <void method="add">
      <string>org.testng.eclipse</string>
     </void>
     <void method="add">
      <string>org.testng.eclipse.maven.feature</string>
     </void>
    </object>
   </void>
   <void method="put">
    <string>https://marketplace.eclipse.org#1789454</string>
    <object class="java.util.ArrayList">
     <void method="add">
      <string>com.codeaffine.gonsole.feature</string>
     </void>
     <void method="add">
      <string>com.codeaffine.gonsole.egit.feature</string>
     </void>
    </object>
   </void>
   <void method="put">
    <string>https://marketplace.eclipse.org#3565771</string>
    <object class="java.util.ArrayList">
     <void method="add">
      <string>com.hybris.hyeclipse.feature</string>
     </void>
    </object>
   </void>
   <void method="put">
    <string>https://marketplace.eclipse.org#2593184</string>
    <object class="java.util.ArrayList">
     <void method="add">
      <string>org.eclipse.embedcdt.managedbuild.cross.arm</string>
     </void>
     <void method="add">
      <string>org.eclipse.embedcdt.managedbuild.cross.riscv</string>
     </void>
     <void method="add">
      <string>org.eclipse.embedcdt.codered</string>
     </void>
     <void method="add">
      <string>org.eclipse.embedcdt.debug.gdbjtag.jlink</string>
     </void>
     <void method="add">
      <string>org.eclipse.embedcdt.debug.gdbjtag.openocd</string>
     </void>
     <void method="add">
      <string>org.eclipse.embedcdt.debug.gdbjtag.pyocd</string>
     </void>
     <void method="add">
      <string>org.eclipse.embedcdt.debug.gdbjtag.qemu</string>
     </void>
     <void method="add">
      <string>org.eclipse.embedcdt.templates.stm</string>
     </void>
     <void method="add">
      <string>org.eclipse.embedcdt.templates.sifive</string>
     </void>
     <void method="add">
      <string>org.eclipse.embedcdt.templates.ad</string>
     </void>
     <void method="add">
      <string>org.eclipse.embedcdt.packs</string>
     </void>
     <void method="add">
      <string>org.eclipse.embedcdt.templates.cortexm</string>
     </void>
    </object>
   </void>
   <void method="put">
    <string>https://marketplace.eclipse.org#5239166</string>
    <object class="java.util.ArrayList">
     <void method="add">
      <string>Stack_Pasta</string>
     </void>
    </object>
   </void>
   <void method="put">
    <string>https://marketplace.eclipse.org#2192883</string>
    <object class="java.util.ArrayList">
     <void method="add">
      <string>org.wangzw.cppstyle.feature</string>
     </void>
    </object>
   </void>
   <void method="put">
    <string>https://marketplace.eclipse.org#4799014</string>
    <object class="java.util.ArrayList">
     <void method="add">
      <string>com.github.imkrmgn.javadocdecorator.feature</string>
     </void>
    </object>
   </void>
   <void method="put">
    <string>https://marketplace.eclipse.org#1744576</string>
    <object class="java.util.ArrayList">
     <void method="add">
      <string>com.ibm.ws.appconversion_feature.tomcat</string>
     </void>
     <void method="add">
      <string>com.ibm.ws.configmigration.tomcat_feature</string>
     </void>
     <void method="add">
      <string>com.ibm.ws.appconversion_feature.weblogic</string>
     </void>
     <void method="add">
      <string>com.ibm.ws.appconversion_feature.jboss</string>
     </void>
     <void method="add">
      <string>com.ibm.ws.appconversion_feature.oracle</string>
     </void>
     <void method="add">
      <string>com.ibm.ws.migrationtoolkit.cloud.feature</string>
     </void>
     <void method="add">
      <string>com.ibm.ws.appconversion_feature.was2was</string>
     </void>
    </object>
   </void>
  </void>
 </object>
</java>
